spdlog.cp310-win_amd64.pyd
spdlog-2.0.6.data/headers/async.h
spdlog-2.0.6.data/headers/async_logger-inl.h
spdlog-2.0.6.data/headers/async_logger.h
spdlog-2.0.6.data/headers/common-inl.h
spdlog-2.0.6.data/headers/common.h
spdlog-2.0.6.data/headers/formatter.h
spdlog-2.0.6.data/headers/fwd.h
spdlog-2.0.6.data/headers/logger-inl.h
spdlog-2.0.6.data/headers/logger.h
spdlog-2.0.6.data/headers/pattern_formatter-inl.h
spdlog-2.0.6.data/headers/pattern_formatter.h
spdlog-2.0.6.data/headers/spdlog-inl.h
spdlog-2.0.6.data/headers/spdlog.h
spdlog-2.0.6.data/headers/stopwatch.h
spdlog-2.0.6.data/headers/tweakme.h
spdlog-2.0.6.data/headers/version.h
spdlog-2.0.6.data/headers/cfg/argv.h
spdlog-2.0.6.data/headers/cfg/env.h
spdlog-2.0.6.data/headers/cfg/helpers-inl.h
spdlog-2.0.6.data/headers/cfg/helpers.h
spdlog-2.0.6.data/headers/details/backtracer-inl.h
spdlog-2.0.6.data/headers/details/backtracer.h
spdlog-2.0.6.data/headers/details/circular_q.h
spdlog-2.0.6.data/headers/details/console_globals.h
spdlog-2.0.6.data/headers/details/file_helper-inl.h
spdlog-2.0.6.data/headers/details/file_helper.h
spdlog-2.0.6.data/headers/details/fmt_helper.h
spdlog-2.0.6.data/headers/details/log_msg-inl.h
spdlog-2.0.6.data/headers/details/log_msg.h
spdlog-2.0.6.data/headers/details/log_msg_buffer-inl.h
spdlog-2.0.6.data/headers/details/log_msg_buffer.h
spdlog-2.0.6.data/headers/details/mpmc_blocking_q.h
spdlog-2.0.6.data/headers/details/null_mutex.h
spdlog-2.0.6.data/headers/details/os-inl.h
spdlog-2.0.6.data/headers/details/os.h
spdlog-2.0.6.data/headers/details/periodic_worker-inl.h
spdlog-2.0.6.data/headers/details/periodic_worker.h
spdlog-2.0.6.data/headers/details/registry-inl.h
spdlog-2.0.6.data/headers/details/registry.h
spdlog-2.0.6.data/headers/details/synchronous_factory.h
spdlog-2.0.6.data/headers/details/tcp_client-windows.h
spdlog-2.0.6.data/headers/details/tcp_client.h
spdlog-2.0.6.data/headers/details/thread_pool-inl.h
spdlog-2.0.6.data/headers/details/thread_pool.h
spdlog-2.0.6.dist-info/LICENSE
spdlog-2.0.6.dist-info/METADATA
spdlog-2.0.6.dist-info/WHEEL
spdlog-2.0.6.dist-info/top_level.txt
spdlog-2.0.6.dist-info/RECORD
