Metadata-Version: 2.1
Name: spdlog
Version: 2.0.6
Summary: python wrapper around C++ spdlog logging library (https://github.com/bodgergely/spdlog-python)
Home-page: UNKNOWN
Author: Gergely Bod
Author-email: bodgergely@hotmail.com
License: MIT
Platform: UNKNOWN
License-File: LICENSE
